matchescu/matching/__init__.py
matchescu/matching/attribute/__init__.py
matchescu/matching/attribute/_match.py
matchescu/matching/attribute/_match_result.py
matchescu/matching/attribute/_typing.py
matchescu/matching/config/__init__.py
matchescu/matching/config/_record_linkage.py
matchescu/matching/entity_reference/__init__.py
matchescu/matching/entity_reference/_attr_spec.py
matchescu/matching/entity_reference/_comparison.py
matchescu/matching/evaluation/__init__.py
matchescu/matching/evaluation/datasets/__init__.py
matchescu/matching/evaluation/datasets/_magellan.py
matchescu/matching/matchers/__init__.py
matchescu/matching/matchers/deterministic/__init__.py
matchescu/matching/matchers/deterministic/_ppjoin.py
matchescu/matching/matchers/ml/__init__.py
matchescu/matching/matchers/ml/ditto/__init__.py
matchescu/matching/matchers/ml/ditto/_const.py
matchescu/matching/matchers/ml/ditto/_ditto_module.py
matchescu/matching/matchers/ml/ditto/_ditto_similarity.py
matchescu/matching/matchers/ml/ditto/_ref_adapter.py
matchescu/matching/matchers/ml/ditto/_torch_util.py
matchescu/matching/matchers/ml/ditto/training/__init__.py
matchescu/matching/matchers/ml/ditto/training/__main__.py
matchescu/matching/matchers/ml/ditto/training/_config.py
matchescu/matching/matchers/ml/ditto/training/_datasets.py
matchescu/matching/matchers/ml/ditto/training/_evaluator.py
matchescu/matching/matchers/ml/ditto/training/_logging.py
matchescu/matching/matchers/ml/ditto/training/_trainer.py
matchescu/matching/matchers/ml/symmetric-transformers.md
matchescu/matching/matchers/probabilistic/__init__.py
matchescu/matching/matchers/probabilistic/_fellegi_sunter.py
matchescu/matching/similarity/__init__.py
matchescu/matching/similarity/_bucketed.py
matchescu/matching/similarity/_common.py
matchescu/matching/similarity/_exact_match.py
matchescu/matching/similarity/_learned_levenshtein.py
matchescu/matching/similarity/_numeric.py
matchescu/matching/similarity/_string.py
matchescu/py.typed
matchescu_matching-0.15.3.dist-info/LICENSE
matchescu_matching-0.15.3.dist-info/METADATA
matchescu_matching-0.15.3.dist-info/WHEEL
matchescu_matching-0.15.3.dist-info/entry_points.txt
matchescu_matching-0.15.3.dist-info/RECORD
